LICENSE
MANIFEST.in
README.md
Readme.md
setup.cfg
setup.py
luwiji/__init__.py
luwiji.egg-info/PKG-INFO
luwiji.egg-info/SOURCES.txt
luwiji.egg-info/dependency_links.txt
luwiji.egg-info/requires.txt
luwiji.egg-info/top_level.txt
luwiji/adaptive_boosting/__init__.py
luwiji/adaptive_boosting/_base.py
luwiji/adaptive_boosting/_demo.py
luwiji/adaptive_boosting/_illustration.py
luwiji/adaptive_boosting/assets/algoritma.png
luwiji/autoencoder/__init__.py
luwiji/autoencoder/_base.py
luwiji/autoencoder/_illustration.py
luwiji/autoencoder/assets/conv_ae.png
luwiji/autoencoder/assets/denoise_document.png
luwiji/autoencoder/assets/denoise_document_train.png
luwiji/autoencoder/assets/play_card.png
luwiji/bias_variance_tradeoff/__init__.py
luwiji/bias_variance_tradeoff/_base.py
luwiji/bias_variance_tradeoff/_demo.py
luwiji/bias_variance_tradeoff/_illustration.py
luwiji/bias_variance_tradeoff/assets/bias_var_tradeoff.png
luwiji/bias_variance_tradeoff/assets/just_right.png
luwiji/cluster/__init__.py
luwiji/cluster/_base.py
luwiji/cluster/_demo.py
luwiji/cluster/_illustration.py
luwiji/cluster/assets/ahc.png
luwiji/cluster/assets/cluster_distance.png
luwiji/cluster/assets/dendrogram.png
luwiji/cnn/__init__.py
luwiji/cnn/_base.py
luwiji/cnn/_illustration.py
luwiji/cnn/assets/blur_avg.png
luwiji/cnn/assets/combination.png
luwiji/cnn/assets/conv_ex1.png
luwiji/cnn/assets/conv_ex2.jpg
luwiji/cnn/assets/conv_ex3.gif
luwiji/cnn/assets/conv_ex4.gif
luwiji/cnn/assets/flower.png
luwiji/cnn/assets/goal.png
luwiji/cnn/assets/nn_vs_cnn.png
luwiji/cnn/assets/padding.png
luwiji/cnn/assets/padding_same.png
luwiji/cnn/assets/partial_con.png
luwiji/cnn/assets/pooling.jpg
luwiji/cnn/assets/stride.png
luwiji/cnn/assets/translation_invariance.png
luwiji/dataset/__init__.py
luwiji/dataset/regression.py
luwiji/dataset/svm.py
luwiji/dimensionality_reduction/__init__.py
luwiji/dimensionality_reduction/_base.py
luwiji/dimensionality_reduction/_demo.py
luwiji/dimensionality_reduction/_illustration.py
luwiji/dimensionality_reduction/assets/dimensi_beras.png
luwiji/dimensionality_reduction/assets/dimensionality_reduction.png
