Metadata-Version: 2.1
Name: luwiji
Version: 1.2.4
Summary: LuWiji is a package full of machine learning illustrations and widgets
Home-page: https://github.com/WiraDKP/luwiji
Author: Wira Dharma Kencana Putra
Author-email: wiradharma_kencanaputra@yahoo.com
License: BSD
Keywords: machine learning ml widget luwiji indonesia
Classifier: Programming Language :: Python :: 3.6
Classifier: Intended Audience :: Developers
Classifier: Intended Audience :: Education
Classifier: Intended Audience :: Information Technology
Classifier: Intended Audience :: Science/Research
Classifier: Topic :: Scientific/Engineering :: Artificial Intelligence
Classifier: Natural Language :: Indonesian
Classifier: Natural Language :: English
Requires-Python: >=3.6.7
License-File: LICENSE
Requires-Dist: numpy
Requires-Dist: scipy
Requires-Dist: pandas
Requires-Dist: scikit-learn
Requires-Dist: matplotlib
Requires-Dist: ipywidgets
Requires-Dist: jcopml
Requires-Dist: pillow
Requires-Dist: networkx
